pytest_reqs.py
pytest_reqs-0.2.1.dist-info/LICENSE
pytest_reqs-0.2.1.dist-info/METADATA
pytest_reqs-0.2.1.dist-info/WHEEL
pytest_reqs-0.2.1.dist-info/entry_points.txt
pytest_reqs-0.2.1.dist-info/top_level.txt
pytest_reqs-0.2.1.dist-info/RECORD
