Metadata-Version: 2.1
Name: pytest-reqs
Version: 0.2.1
Summary: pytest plugin to check pinned requirements
Home-page: https://github.com/di/pytest-reqs
Author: Dustin Ingram
Author-email: github@dustingram.com
License: MIT license
Platform: UNKNOWN
Classifier: Framework :: Pytest
Classifier: Programming Language :: Python
Classifier: Programming Language :: Python :: 2.7
Classifier: Programming Language :: Python :: 3.5
Classifier: Programming Language :: Python :: 3.6
Classifier: Programming Language :: Python :: 3.7
Requires-Dist: pytest (>=2.4.2)
Requires-Dist: packaging (>=17.1)
Requires-Dist: pip-api (>=0.0.2)
